LICENSE
MANIFEST.in
README.md
setup.cfg
setup.py
xkcd.py
xkcd.egg-info/PKG-INFO
xkcd.egg-info/SOURCES.txt
xkcd.egg-info/dependency_links.txt
xkcd.egg-info/top_level.txt