Metadata-Version: 1.1
Name: xkcd
Version: 2.3.1
Summary: Library to access xkcd.com
Home-page: https://github.com/TC01/xkcd
Author: Ben Rosser
Author-email: rosser.bjr@gmail.com
License: MIT
Keywords: xkcd webcomic
Platform: UNKNOWN
Classifier: Development Status :: 5 - Production/Stable
Classifier: Intended Audience :: Developers
Classifier: Intended Audience :: End Users/Desktop
Classifier: Topic :: Software Development :: Libraries
Classifier: Topic :: Internet :: WWW/HTTP
Classifier: Topic :: Internet :: WWW/HTTP :: Dynamic Content
Classifier: License :: OSI Approved :: MIT License
Classifier: Programming Language :: Python :: 2
Classifier: Programming Language :: Python :: 2.7
Classifier: Programming Language :: Python :: 3
Classifier: Programming Language :: Python :: 3.3
